{
    "criteria": {
        "use_beacon":{
            "trigger": "any_block_use",
            "conditions": {
                "location": [
                    {
                        "condition":"location_check",
                        "predicate": {
                            "block": {
                                "blocks": "beacon"
                            }
                        }
                    }
                ]
            }
        }
    },
    "rewards": {
        "function": "beacon_tweak:used"
    }
}